hooku/__init__.py
hooku/hooku.py
hooku-1.1.0.dist-info/LICENSE.txt
hooku-1.1.0.dist-info/METADATA
hooku-1.1.0.dist-info/WHEEL
hooku-1.1.0.dist-info/top_level.txt
hooku-1.1.0.dist-info/RECORD
